robot_base/__init__.py
robot_base/index.py
robot_base/marker_window.py
robot_base/rectangle_window.py
robot_base/tip_window.py
robot_base-0.3.2.dist-info/METADATA
robot_base-0.3.2.dist-info/WHEEL
robot_base-0.3.2.dist-info/RECORD
