Metadata-Version: 2.4
Name: robot_base
Version: 0.3.2
Summary: robot base tools
Author: mance
Classifier: License :: OSI Approved :: MIT License
Classifier: Operating System :: OS Independent
Classifier: Programming Language :: Python :: 3
Requires-Python: >=3.11
Requires-Dist: loguru
